setdir.py
setdir-1.1.1.dist-info/LICENSE
setdir-1.1.1.dist-info/METADATA
setdir-1.1.1.dist-info/WHEEL
setdir-1.1.1.dist-info/RECORD
